patientsim/__init__.py
patientsim/admin_staff.py
patientsim/assets/prompt/ed_doctor_sys.txt
patientsim/assets/prompt/ed_patient_sys.txt
patientsim/assets/prompt/ed_terminate_user.txt
patientsim/assets/prompt/ed_uti_patient_sys.txt
patientsim/assets/prompt/op_patient_sys.txt
patientsim/assets/prompt/op_staff_sys.txt
patientsim/assets/prompt/op_terminate_user.txt
patientsim/checker.py
patientsim/client/__init__.py
patientsim/client/google_client.py
patientsim/client/google_vertex_client.py
patientsim/client/openai_azure_client.py
patientsim/client/openai_client.py
patientsim/client/vllm_client.py
patientsim/doctor.py
patientsim/environment/__init__.py
patientsim/environment/ed_simulation.py
patientsim/environment/op_simulation.py
patientsim/patient.py
patientsim/registry/detection_key.py
patientsim/registry/persona.py
patientsim/registry/term.py
patientsim/utils/__init__.py
patientsim/utils/common_utils.py
patientsim/utils/desc_utils.py
patientsim/version.txt
patientsim-0.2.0.dist-info/LICENSE
patientsim-0.2.0.dist-info/METADATA
patientsim-0.2.0.dist-info/WHEEL
patientsim-0.2.0.dist-info/RECORD
