Metadata-Version: 2.1
Name: patientsim
Version: 0.2.0
Summary: A Python package for simulating patient interactions.
License: BSD-3-Clause
Author: Jun-Min Lee
Author-email: ljm56897@gmail.com
Requires-Python: >=3.11,<3.13
Classifier: License :: OSI Approved :: BSD License
Classifier: Programming Language :: Python :: 3
Classifier: Programming Language :: Python :: 3.11
Classifier: Programming Language :: Python :: 3.12
Requires-Dist: dotenv (==0.9.9)
Requires-Dist: google-genai (==1.19.0)
Requires-Dist: openai (>=1.99.1)
Requires-Dist: vllm (>=0.10.2,<0.11.0)
Project-URL: Source, https://github.com/ljm565/patientsim-pkg
